diagramTool/__init__.py
diagramTool/__main__.py
diagramTool/main.py
diagramTool/python/__init__.py
diagramTool/python/python.py
diagramTool/svg/__init__.py
diagramTool/svg/customTypes.py
diagramTool/svg/main.py
diagramTool/svg/svg.py
diagramTool/svg/utils.py
DiagramTool-1.0.2.dist-info/METADATA
DiagramTool-1.0.2.dist-info/WHEEL
DiagramTool-1.0.2.dist-info/entry_points.txt
DiagramTool-1.0.2.dist-info/top_level.txt
DiagramTool-1.0.2.dist-info/RECORD
