Metadata-Version: 2.1
Name: DiagramTool
Version: 1.0.2
Summary: A tool to create diagrams from code
Author-email: Antoine Buirey <antoine.buirey@gmail.com>
Project-URL: homepage, https://github.com/T0ine34/DiagramTool
Project-URL: issues, https://github.com/T0ine34/DiagramTool/issues
Project-URL: source, https://github.com/T0ine34/DiagramTool
Classifier: Programming Language :: Python :: 3
Classifier: License :: OSI Approved :: MIT License
Classifier: Operating System :: OS Independent
Requires-Python: >=3.11
Requires-Dist: gamuLogger >=2.0.6
Requires-Dist: lxml >=4.6.3
